cuapi_wrapper/__init__.py
cuapi_wrapper/_modidx.py
cuapi_wrapper/companies.py
cuapi_wrapper/core.py
cuapi_wrapper-0.0.1.dist-info/LICENSE
cuapi_wrapper-0.0.1.dist-info/METADATA
cuapi_wrapper-0.0.1.dist-info/WHEEL
cuapi_wrapper-0.0.1.dist-info/entry_points.txt
cuapi_wrapper-0.0.1.dist-info/top_level.txt
cuapi_wrapper-0.0.1.dist-info/RECORD
